testrepo2/__init__.py
testrepo2/_utils/__init__.py
testrepo2-0.0.0.dist-info/LICENSE
testrepo2-0.0.0.dist-info/LICENSE.txt
testrepo2-0.0.0.dist-info/METADATA
testrepo2-0.0.0.dist-info/WHEEL
testrepo2-0.0.0.dist-info/top_level.txt
testrepo2-0.0.0.dist-info/RECORD
