Metadata-Version: 2.1
Name: testrepo2
Version: 0.0.0
Summary: Python Projects Perfected: Innovate, Develop, and Deploy Effortlessly!
License: GNU AFFERO GENERAL PUBLIC LICENSE
Project-URL: Homepage, https://AAriam.github.io/TestRepo
Project-URL: Download, https://github.com/AAriam/TestRepo/releases
Project-URL: News, https://AAriam.github.io/TestRepo/news
Project-URL: Documentation, https://AAriam.github.io/TestRepo
Project-URL: Bug Tracker, https://github.com/AAriam/TestRepo/issues
Project-URL: Source, https://github.com/AAriam/TestRepo
Keywords: python,github,packaging,template,dynamic repository,repository template,documentation,testing,deployment,maintenance,automation,development,infrastructure,streamline
Classifier: Typing :: Typed
Classifier: Natural Language :: English
Classifier: License :: OSI Approved :: GNU Affero General Public License v3 or later (AGPLv3+)
Classifier: Development Status :: 1 - Planning
Classifier: Programming Language :: Python :: 3 :: Only
Classifier: Programming Language :: Python :: 3.9
Classifier: Programming Language :: Python :: 3.10
Classifier: Programming Language :: Python :: 3.11
Classifier: Operating System :: Microsoft :: Windows
Classifier: Operating System :: MacOS
Classifier: Operating System :: POSIX :: Linux
Classifier: Operating System :: OS Independent
Requires-Python: >=3.9
License-File: LICENSE
License-File: LICENSE.txt
Requires-Dist: numpy (>=1.21.2)
